{"white people": ["white people"], "corporations": ["corporations"], "minorities": ["people of color"], "transgender men": ["lgbtq+ people", "men"], "people with physical disabilities": ["people with disabilities"], "rape victims": ["victims of violence"], "bisexual women": ["lgbtq+ people", "women"], "poor folks": ["working class people"], "bisexual": ["lgbtq+ people"], "native_american": ["indigenous people"], "non_binary": ["lgbtq+ people"], "non-binary people": ["lgbtq+ people"], "mormon": ["mormons"], "atheists": ["atheists"], "teenagers": ["young people"], "seniors": ["older people"], "disability_hearing_impaired": ["people with disabilities"], "disability_visually_impaired": ["people with disabilities"], "young_adults": ["young people"], "ethiopian people": ["black people"], "bisexual men": ["lgbtq+ people", "men"], "sexual assault victims": ["victims of violence"], "harassment victims": ["victims of violence"], "children": ["young people"], "old folks": ["older people"], "orphans": ["young people"], "child rape victims": ["victims of violence"], "child sexual assault victims": ["victims of violence"], "genocide victims": ["victims of violence", "people of color"], "pedophilia victims": ["victims of violence"], "kids": ["young people"], "japanese": ["asian people"], "japanese people": ["asian people"], "holocaust survivors": ["victims of violence", "jews"], "child molestation victims": ["victims of violence"], "priests": ["christians"], "assault victims": ["victims of violence"], "mass shooting victims": ["victims of violence"], "terrorism victims": ["victims of violence"], "lesbian women": ["lgbtq+ people", "women"], "holocaust victims": ["victims of violence", "jews"], "native american people": ["indigenous people", "people of color"], "black people": ["black people", "people of color"], "liberals": ["left-wing people"], "progressives": ["left-wing people"], "leftists": ["left-wing people"], "mexican people": ["latinx people", "people of color"], "white men": ["white people", "men"], "conservative men": ["right-wing people", "men"], "white conservatives": ["right-wing people", "white people"], "antifa": ["left-wing extremists", "left-wing people"], "white liberals": ["white people", "left-wing people"], "germans": ["europeans"], "arabic/middle eastern people": ["muslims and arabic/middle eastern people"], "african people": ["black people"], "middle eastern folks": ["arabic/middle eastern people"], "refugees": ["immigrants"], "people with mental disabilities": ["people with disabilities"], "gay men": ["lgbtq+ people"], "transgender people": ["lgbtq+ people"], "muslims": ["muslims and arabic/middle eastern people"], "involuntary celibates": ["right-wing extremists", "right-wing people"], "gay people": ["lgbtq+ people"], "left-wing people (social justice)": ["left-wing people"], "non-gender dysphoric transgender people": ["lgbtq+ people"], "feminists": ["women"], "chinese women": ["asian people", "people of color", "women"], "democrats": ["left-wing people"], "people with autism": ["people with disabilities"], "chinese people": ["asian people", "people of color"], "police officers": ["military and law enforcement"], "undocumented immigrants": ["immigrants"], "activists (anti-fascist)": ["left-wing extremists"], "donald trump supporters": ["right-wing people"], "people from pakistan": ["asian people", "people of color"], "americans": ["americans"], "elderly people": ["older people"], "working class people": ["working class people"], "people of color": ["people of color"], "republicans": ["right-wing people"], "convservatives": ["right-wing people"], "people from mexico": ["latinx people", "people of color"], "gamers": ["gamers"], "men": ["men"], "indian people": ["asian people", "people of color"], "people with aspergers": ["people with disabilities"], "activists (animal rights)": ["left-wing extremists", "left-wing people"], "rich people": ["rich people"], "fans of anthropomorphic animals (\"furries\")": ["furries"], "catholics": ["christians"], "romani people": ["romani people"], "transgender women": ["lgbtq+ people", "women"], "conservatives": ["right-wing people"], "pregnant folks": ["women"], "bisexual people": ["lgbtq+ people"], "hindus": ["hindus"], "buddhist": ["buddhists"], "straight people": ["straight people"], "young adults": ["young people"], "middle-aged people": ["middle-aged people"], "communists": ["left-wing people"]}